napari_imaris_loader/__init__.py
napari_imaris_loader/_version.py
napari_imaris_loader/reader.py
napari_imaris_loader/resolution_change_widget.py
napari_imaris_loader/_tests/__init__.py
napari_imaris_loader/_tests/test_reader.py
napari_imaris_loader-0.1.8.dist-info/LICENSE
napari_imaris_loader-0.1.8.dist-info/METADATA
napari_imaris_loader-0.1.8.dist-info/WHEEL
napari_imaris_loader-0.1.8.dist-info/entry_points.txt
napari_imaris_loader-0.1.8.dist-info/top_level.txt
napari_imaris_loader-0.1.8.dist-info/RECORD
