Metadata-Version: 2.1
Name: napari-imaris-loader
Version: 0.1.8
Summary: Napari plugin for loading Bitplane imaris files '.ims'
Home-page: https://github.com/AlanMWatson/napari-imaris-loader
Author: Alan M Watson
Author-email: alan.watson@pitt.edu
License: BSD-3-Clause
Project-URL: Bug Tracker, https://github.com/AlanMWatson/napari-imaris-loader/issues
Project-URL: Documentation, https://github.com/AlanMWatson/napari-imaris-loader#README.md
Project-URL: Source Code, https://github.com/AlanMWatson/napari-imaris-loader
Project-URL: User Support, https://github.com/AlanMWatson/napari-imaris-loader/issues
Platform: UNKNOWN
Classifier: Development Status :: 2 - Pre-Alpha
Classifier: Intended Audience :: Developers
Classifier: Framework :: napari
Classifier: Topic :: Software Development :: Testing
Classifier: Programming Language :: Python
Classifier: Programming Language :: Python :: 3
Classifier: Programming Language :: Python :: 3.8
Classifier: Programming Language :: Python :: 3.9
Classifier: Operating System :: OS Independent
Classifier: License :: OSI Approved :: BSD License
Requires-Python: >=3.8
License-File: LICENSE
Requires-Dist: napari[all]
Requires-Dist: napari-plugin-engine (>=0.1.4)
Requires-Dist: imaris-ims-file-reader (>=0.1.5)
Requires-Dist: numpy
Requires-Dist: h5py
Requires-Dist: dask
